resource_man/__init__.py
resource_man/__meta__.py
resource_man/importlib_interface.py
resource_man/interface.py
resource_man/pyinstaller.py
resource_man/qt.py
resource_man/__pycache__/__init__.cpython-310.pyc
resource_man/__pycache__/__meta__.cpython-310.pyc
resource_man/__pycache__/importlib_interface.cpython-310.pyc
resource_man/__pycache__/interface.cpython-310.pyc
resource_man/__pycache__/qt.cpython-310.pyc
resource_man-2.2.8.dist-info/LICENSE
resource_man-2.2.8.dist-info/METADATA
resource_man-2.2.8.dist-info/WHEEL
resource_man-2.2.8.dist-info/top_level.txt
resource_man-2.2.8.dist-info/RECORD
