Metadata-Version: 2.1
Name: resource-man
Version: 2.2.8
Summary: Python resource manager to work with the standard library for regular python code and executables.
Home-page: https://github.com/justengel/resource_man
Author: Justin Engel
Author-email: jtengel08@gmail.com
License: MIT
Download-URL: https://github.com/justengel/resource_man/archive/v2.2.8.tar.gz
Keywords: importlib_resources importlib.resources importlib resources
Platform: any
Classifier: Programming Language :: Python
Classifier: Programming Language :: Python :: 3
Classifier: Operating System :: OS Independent
License-File: LICENSE
Provides-Extra: qt
Requires-Dist: dynamicmethod (>=1.1.0) ; extra == 'qt'
Requires-Dist: qtpy (>=1.9.0) ; extra == 'qt'
